CopBET/CopBET.py
CopBET/__init__.py
copbet-1.0.2.dist-info/licenses/LICENSE.txt
copbet-1.0.2.dist-info/METADATA
copbet-1.0.2.dist-info/WHEEL
copbet-1.0.2.dist-info/top_level.txt
copbet-1.0.2.dist-info/RECORD
