Metadata-Version: 2.4
Name: CopBET
Version: 1.0.2
Summary: A Python wrapper for the Copenhagen Brain Entropy Toolbox (CopBET), originally developed by Anders S. Olsen.
Home-page: https://github.com/shuds13/pyexample
Author: Viswanath Missula
Author-email: vmissul1@jh.edu
License: GNU General Public License 3.0
Classifier: Development Status :: 4 - Beta
Classifier: Intended Audience :: Science/Research
Classifier: License :: OSI Approved :: GNU General Public License v3 (GPLv3)
Classifier: Operating System :: OS Independent
Classifier: Programming Language :: Python :: 3.11
Classifier: Programming Language :: Python :: 3.12
License-File: LICENSE.txt
Requires-Dist: numpy
Requires-Dist: matlab
Requires-Dist: matplotlib
Requires-Dist: nibabel
Requires-Dist: pandas
Requires-Dist: scipy
Dynamic: author
Dynamic: author-email
Dynamic: classifier
Dynamic: description
Dynamic: description-content-type
Dynamic: home-page
Dynamic: license
Dynamic: license-file
Dynamic: requires-dist
Dynamic: summary
